scflcore/__init__.py
scflcore/core.py
minecraftManager-0.0.1.dist-info/METADATA
minecraftManager-0.0.1.dist-info/WHEEL
minecraftManager-0.0.1.dist-info/top_level.txt
minecraftManager-0.0.1.dist-info/RECORD
