Metadata-Version: 2.1
Name: minecraftManager
Version: 0.0.1
Summary: Package to help creating and managing minecraft servers
Home-page: UNKNOWN
Author: SScefaLI
Author-email: birka11@list.ru
License: UNKNOWN
Platform: UNKNOWN
Classifier: Programming Language :: Python :: 3
Classifier: License :: OSI Approved :: MIT License
Classifier: Operating System :: OS Independent
Requires-Python: >=3.8
Requires-Dist: mctools
